<?xml version="1.0" encoding="UTF-8"?>
<con:loadUiTest name="LoadTest 1" id="37ffd9af-f3a9-4ee5-9b85-8af3feba3fc8" xmlns:con="http://eviware.com/soapui/config"><con:settings><con:setting id="soapUIObjectSourceId">4d038a06-59fe-453a-8ce9-2406753a23f2</con:setting><con:setting id="convertedFromLoadTestModelItemId">d6f0544b-29c8-414f-a5c7-b77d87d0caaf</con:setting><con:setting id="37ffd9af-f3a9-4ee5-9b85-8af3feba3fc8fileName">LoadTest-1</con:setting></con:settings><con1:loadui-project id="50ef7d59-bc35-4391-9b76-48109b51efc5" label="LoadTest 1" xmlns:con1="http://eviware.com/loadui/config"><con1:properties><con1:property propagates="true" key="ModelItem.description" type="java.lang.String"/><con1:property propagates="true" key="CanvasItem.abortOnFinish" type="java.lang.Boolean">false</con1:property><con1:property propagates="true" key="ModelItem.saveReport" type="java.lang.Boolean">false</con1:property><con1:property propagates="true" key="ModelItem.reportFolder" type="java.lang.String"/><con1:property propagates="true" key="ModelItem.reportFormat" type="java.lang.String"/><con1:property propagates="true" key="Temporary project" type="java.lang.String"/><con1:property propagates="true" key="ModelItem.rate" type="java.lang.Long">10</con1:property><con1:property propagates="true" key="ModelItem.loadDistributionType" type="com.smartbear.load.facade.LoadDistributionType">PerScenario</con1:property><con1:property propagates="true" key="ModelItem.remoteMode" type="java.lang.String"/></con1:properties><con1:attributes><con1:property key="limits">Time=60;</con1:property></con1:attributes><con1:addons/><con1:scene label="New Scenario" id="ec134bc5-cf92-4b96-8c14-f5fd30e00561" version="29"><con1:properties><con1:property propagates="true" key="ModelItem.description" type="java.lang.String"/><con1:property propagates="true" key="CanvasItem.abortOnFinish" type="java.lang.Boolean">false</con1:property><con1:property propagates="true" key="SceneItem.followProject" type="java.lang.Boolean">true</con1:property><con1:property propagates="true" key="SceneItem.scenarioRatePercentage" type="java.lang.Long">100</con1:property><con1:property propagates="true" key="SceneItem.scenarioRateSpecific" type="java.lang.Long">10</con1:property></con1:properties><con1:attributes><con1:property key="limits">Time=60;</con1:property></con1:attributes><con1:addons/><con1:component type="com.eviware.loadui.impl.component.IntervalComponent" label="Interval 1" id="29896fc9-488a-43a0-8142-c13a7d5bc3bd" category="Scheduler"><con1:properties><con1:property propagates="true" key="ModelItem.description" type="java.lang.String"/><con1:property propagates="true" key="stateProperty" type="java.lang.Boolean">true</con1:property><con1:property propagates="true" key="startAt" type="java.lang.Long">0</con1:property><con1:property propagates="true" key="duration" type="java.lang.Long">5</con1:property><con1:property propagates="true" key="unit" type="java.lang.String">Sec</con1:property><con1:property propagates="true" key="mode" type="java.lang.String">Single</con1:property><con1:property propagates="true" key="defaultMode" type="java.lang.Boolean">true</con1:property></con1:properties><con1:attributes><con1:property key="com.eviware.loadui.api.model.ComponentItem@type">Interval</con1:property></con1:attributes><con1:addons/></con1:component><con1:component type="com.eviware.loadui.impl.component.generators.FixedVU" label="Fixed Load 2" id="106175c8-0b38-47f7-a9cc-9b1a7b01b8bd" category="Generators"><con1:properties><con1:property propagates="true" key="ModelItem.description" type="java.lang.String"/><con1:property propagates="true" key="stateProperty" type="java.lang.Boolean">true</con1:property><con1:property propagates="true" key="limitVU" type="java.lang.Long">10</con1:property><con1:property propagates="true" key="load" type="java.lang.Long">5</con1:property><con1:property propagates="true" key="interval" type="java.lang.Long">1000</con1:property></con1:properties><con1:attributes><con1:property key="com.eviware.loadui.api.model.ComponentItem@type">Fixed Load</con1:property></con1:attributes><con1:addons/></con1:component><con1:component type="com.eviware.loadui.components.soapui.SoapUISamplerComponent" label="Copy of PerformanceTestingDev:Main" id="a3c0452d-5588-4e14-9dd0-56efb0c60cce" category="Runners"><con1:properties><con1:property propagates="true" key="ModelItem.description" type="java.lang.String"/><con1:property propagates="true" key="concurrentSamples" type="java.lang.Long">1000</con1:property><con1:property propagates="true" key="property_name_is_not_relevant_for_private_property" type="java.lang.Long">9223372036854775807</con1:property><con1:property propagates="true" key="maxQueueSize" type="java.lang.Long">1000</con1:property><con1:property propagates="true" key="countDiscarded" type="java.lang.Boolean">false</con1:property><con1:property propagates="true" key="disabledTestSteps" type="java.lang.String"/><con1:property propagates="true" key="_thinkTime" type="java.lang.Long">0</con1:property><con1:property propagates="true" key="ReadyApiTestCase" type="com.eviware.soapui.impl.wsdl.testcase.WsdlTestCase">4d038a06-59fe-453a-8ce9-2406753a23f2</con1:property><con1:property propagates="true" key="raiseError" type="java.lang.Boolean">true</con1:property><con1:property propagates="true" key="outputTestCaseProperties" type="java.lang.Boolean">true</con1:property><con1:property propagates="true" key="OutputLevel" type="java.lang.String">TestCase only</con1:property><con1:property propagates="true" key="closeConnectionsAfterRequest" type="java.lang.Boolean">false</con1:property><con1:property propagates="true" key="disableSoapuiAssertions" type="java.lang.Boolean">false</con1:property><con1:property propagates="true" key="forceShareDatasources" type="java.lang.Boolean">true</con1:property></con1:properties><con1:attributes><con1:property key="com.eviware.loadui.api.model.ComponentItem@type">Ready API TestCase Runner</con1:property></con1:attributes><con1:addons/></con1:component><con1:connection outputTerminalId="29896fc9-488a-43a0-8142-c13a7d5bc3bd/outgoingTerminal" inputTerminalId="106175c8-0b38-47f7-a9cc-9b1a7b01b8bd/stateTerminal"/><con1:connection outputTerminalId="106175c8-0b38-47f7-a9cc-9b1a7b01b8bd/triggerTerminal" inputTerminalId="a3c0452d-5588-4e14-9dd0-56efb0c60cce/triggerTerminal"/><con1:connection outputTerminalId="a3c0452d-5588-4e14-9dd0-56efb0c60cce/runningTerminal" inputTerminalId="106175c8-0b38-47f7-a9cc-9b1a7b01b8bd/Sample Count"/></con1:scene><con1:statistics><con1:page title="DefaultLoadUIStatisticPage"><con1:chartGroup type="com.eviware.loadui.api.statistics.model.chart.line.LineChartView" title="" groupType="Monitors"><con1:attributes><con1:property key="GroupId">e377d7f0-7cc8-4d2a-8a1f-a9c1d110f5c3</con1:property></con1:attributes></con1:chartGroup></con1:page></con1:statistics></con1:loadui-project><con:loadUITestScenario projectId="50ef7d59-bc35-4391-9b76-48109b51efc5" scenarioId="ec134bc5-cf92-4b96-8c14-f5fd30e00561" name="New Scenario" id="ce323c07-ae2d-4783-a13a-c2e21028e40d"><con:settings/></con:loadUITestScenario><con:loadUIPanelData id="911c7304-8141-4464-9f10-fdf03c0b3958"><con:panel>Log</con:panel><con:data><con:paramName>column_width@Timestamp</con:paramName><con:paramValue>96</con:paramValue></con:data><con:data><con:paramName>column_visible@Timestamp</con:paramName><con:paramValue>true</con:paramValue></con:data><con:data><con:paramName>column_width@ID</con:paramName><con:paramValue>65</con:paramValue></con:data><con:data><con:paramName>column_visible@ID</con:paramName><con:paramValue>true</con:paramValue></con:data><con:data><con:paramName>column_width@Status</con:paramName><con:paramValue>61</con:paramValue></con:data><con:data><con:paramName>column_visible@Status</con:paramName><con:paramValue>true</con:paramValue></con:data><con:data><con:paramName>column_width@TriggerTimestamp</con:paramName><con:paramValue>96</con:paramValue></con:data><con:data><con:paramName>column_visible@TriggerTimestamp</con:paramName><con:paramValue>true</con:paramValue></con:data><con:data><con:paramName>column_width@TimeTaken</con:paramName><con:paramValue>134</con:paramValue></con:data><con:data><con:paramName>column_visible@TimeTaken</con:paramName><con:paramValue>true</con:paramValue></con:data><con:data><con:paramName>column_width@_wait_time_</con:paramName><con:paramValue>121</con:paramValue></con:data><con:data><con:paramName>column_visible@_wait_time_</con:paramName><con:paramValue>true</con:paramValue></con:data><con:data><con:paramName>column_width@Bytes</con:paramName><con:paramValue>56</con:paramValue></con:data><con:data><con:paramName>column_visible@Bytes</con:paramName><con:paramValue>true</con:paramValue></con:data><con:data><con:paramName>column_width@HTTP Status</con:paramName><con:paramValue>101</con:paramValue></con:data><con:data><con:paramName>column_visible@HTTP Status</con:paramName><con:paramValue>true</con:paramValue></con:data><con:data><con:paramName>column_width@CurrentlyRunning</con:paramName><con:paramValue>88</con:paramValue></con:data><con:data><con:paramName>column_visible@CurrentlyRunning</con:paramName><con:paramValue>true</con:paramValue></con:data><con:data><con:paramName>column_width@Request</con:paramName><con:paramValue>75</con:paramValue></con:data><con:data><con:paramName>column_visible@Request</con:paramName><con:paramValue>false</con:paramValue></con:data><con:data><con:paramName>column_width@Response</con:paramName><con:paramValue>85</con:paramValue></con:data><con:data><con:paramName>column_visible@Response</con:paramName><con:paramValue>false</con:paramValue></con:data><con:data><con:paramName>column_width@soapui_context</con:paramName><con:paramValue>122</con:paramValue></con:data><con:data><con:paramName>column_visible@soapui_context</con:paramName><con:paramValue>false</con:paramValue></con:data></con:loadUIPanelData><con:setupScript xsi:nil="true" xmlns:xsi="http://www.w3.org/2001/XMLSchema-instance"/><con:teardownScript xsi:nil="true" xmlns:xsi="http://www.w3.org/2001/XMLSchema-instance"/><con:reportParameters/></con:loadUiTest>